plone.base-3.1.1-py3.13-nspkg.pth
plone/base/__init__.py
plone/base/batch.py
plone/base/defaultpage.py
plone/base/i18nl10n.py
plone/base/navigationroot.py
plone/base/permissions.py
plone/base/utils.py
plone/base/interfaces/__init__.py
plone/base/interfaces/basetool.py
plone/base/interfaces/breadcrumbs.py
plone/base/interfaces/constrains.py
plone/base/interfaces/content.py
plone/base/interfaces/controlpanel.py
plone/base/interfaces/defaultpage.py
plone/base/interfaces/events.py
plone/base/interfaces/images.py
plone/base/interfaces/installable.py
plone/base/interfaces/interface.py
plone/base/interfaces/language.py
plone/base/interfaces/login.py
plone/base/interfaces/migration.py
plone/base/interfaces/password_reset.py
plone/base/interfaces/patterns.py
plone/base/interfaces/properties.py
plone/base/interfaces/resources.py
plone/base/interfaces/siteroot.py
plone/base/interfaces/structure.py
plone/base/interfaces/syndication.py
plone/base/interfaces/translationservice.py
plone/base/interfaces/workflow.py
plone/base/tests/__init__.py
plone/base/tests/messages.rst
plone/base/tests/test_batch.py
plone/base/tests/test_doctests.py
plone/base/tests/test_i18nl10n.py
plone/base/tests/test_root.py
plone/base/tests/test_utils.py
plone_base-3.1.1.dist-info/METADATA
plone_base-3.1.1.dist-info/WHEEL
plone_base-3.1.1.dist-info/namespace_packages.txt
plone_base-3.1.1.dist-info/top_level.txt
plone_base-3.1.1.dist-info/RECORD
