Metadata-Version: 2.2
Name: plone.base
Version: 3.1.1
Summary: Plone Interface contracts, plus basic features and utilities
Home-page: https://github.com/plone/plone.base
Author: Jens W. Klein
Author-email: jk@kleinundpartner.at
Maintainer: Plone Release Team
Maintainer-email: releaseteam@plone.org
License: GPLv2
Keywords: plone
Classifier: Development Status :: 5 - Production/Stable
Classifier: Environment :: Web Environment
Classifier: Framework :: Plone :: 6.1
Classifier: Framework :: Plone :: Core
Classifier: Framework :: Zope :: 5
Classifier: License :: OSI Approved :: GNU General Public License v2 (GPLv2)
Classifier: Operating System :: OS Independent
Classifier: Programming Language :: Python
Classifier: Programming Language :: Python :: 3.10
Classifier: Programming Language :: Python :: 3.11
Classifier: Programming Language :: Python :: 3.12
Requires-Python: >=3.10
Requires-Dist: setuptools
Requires-Dist: plone.batching
Requires-Dist: plone.registry
Requires-Dist: plone.schema
Requires-Dist: plone.z3cform
Requires-Dist: Products.CMFCore
Requires-Dist: Products.CMFDynamicViewFTI
Requires-Dist: Zope
Provides-Extra: test
Requires-Dist: plone.subrequest; extra == "test"
